sphinxcontrib_visio-2.1.2-py2.7-nspkg.pth
sphinxcontrib/visio.py
sphinxcontrib_visio-2.1.2.dist-info/DESCRIPTION.rst
sphinxcontrib_visio-2.1.2.dist-info/METADATA
sphinxcontrib_visio-2.1.2.dist-info/RECORD
sphinxcontrib_visio-2.1.2.dist-info/WHEEL
sphinxcontrib_visio-2.1.2.dist-info/metadata.json
sphinxcontrib_visio-2.1.2.dist-info/namespace_packages.txt
sphinxcontrib_visio-2.1.2.dist-info/top_level.txt
