Metadata-Version: 2.0
Name: sphinxcontrib-visio
Version: 2.1.2
Summary: Sphinx "visio" extension; embed MS-Visio file (.vsd, .vsdx)
Home-page: https://github.com/visio2img/sphinxcontrib-visio
Author: Takeshi KOMIYA
Author-email: i.tkomiya@gmail.com
License: UNKNOWN
Platform: UNKNOWN
Classifier: Development Status :: 5 - Production/Stable
Classifier: Environment :: Console
Classifier: Environment :: Win32 (MS Windows)
Classifier: Framework :: Sphinx :: Extension
Classifier: License :: OSI Approved :: Apache Software License
Classifier: Operating System :: Microsoft :: Windows
Classifier: Programming Language :: Python
Classifier: Programming Language :: Python :: 2
Classifier: Programming Language :: Python :: 2.7
Classifier: Programming Language :: Python :: 3
Classifier: Programming Language :: Python :: 3.3
Classifier: Programming Language :: Python :: 3.4
Classifier: Topic :: Documentation
Classifier: Topic :: Documentation :: Sphinx
Classifier: Topic :: Multimedia :: Graphics :: Graphics Conversion
Classifier: Topic :: Office/Business :: Office Suites
Classifier: Topic :: Software Development :: Libraries :: Python Modules
Classifier: Topic :: Utilities
Requires-Dist: Sphinx (>=1.0.0)
Requires-Dist: sphinxcontrib-imagehelper
Requires-Dist: visio2img (>=1.2.0)
